ruff_pyspark_filter_linter/__init__.py
ruff_pyspark_filter_linter/linter.py
ruff_pyspark_filter_linter/log_utils.py
tests/__init__.py
tests/test_linter.py
ruff_pyspark_filter_linter-0.1.0.dist-info/LICENSE
ruff_pyspark_filter_linter-0.1.0.dist-info/METADATA
ruff_pyspark_filter_linter-0.1.0.dist-info/WHEEL
ruff_pyspark_filter_linter-0.1.0.dist-info/entry_points.txt
ruff_pyspark_filter_linter-0.1.0.dist-info/top_level.txt
ruff_pyspark_filter_linter-0.1.0.dist-info/RECORD
