Metadata-Version: 2.1
Name: ruff_pyspark_filter_linter
Version: 0.1.0
Summary: Custom Ruff linter to ensure specific filters in PySpark DataFrame creation
Home-page: https://github.com/dhimahi-vavk-fusion/ruff_pyspark_filter_linter
Author: Dhimahi Vavk
Author-email: 
Classifier: Programming Language :: Python :: 3
Classifier: License :: OSI Approved :: MIT License
Classifier: Operating System :: OS Independent
Requires-Python: >=3.6
License-File: LICENSE
Requires-Dist: ruff
Requires-Dist: astunparse
